<?xml version="1.0" encoding="UTF-8"?>
<DB>
	<QREC on="1">
		<A_Type><![CDATA[GW]]></A_Type>
		<UPDATED><![CDATA[Dec 18]]></UPDATED>
		<DEV_COMMENT dir="ltr" esbox="0"><![CDATA[Edited for English by Jeff.Hansman—Dec. 16, 2013]]></DEV_COMMENT>
		<OL_Title dir="ltr" esbox="0"><![CDATA[The Olympics Torch in Space]]></OL_Title>
		<LO_SHORT_DESCRIPT dir="ltr" esbox="0"><![CDATA[Unusual leg of the Olympic torch relay]]></LO_SHORT_DESCRIPT>
		<QUARTER><![CDATA[q1]]></QUARTER>
		<KEY_WORDS dir="ltr" esbox="0"><![CDATA[rocket, space station, near-Earth orbit, docking, spacewalk, torch, relay, to light]]></KEY_WORDS>
		<LANGUAGE><![CDATA[Russian]]></LANGUAGE>
		<THEME><![CDATA[Blue Haze]]></THEME>
		<YEAR><![CDATA[2014]]></YEAR>
		<FL_Title dir="ltr"><![CDATA["Космический" огонь Олимпиады]]></FL_Title>
		<XL_Title dir="ltr"><![CDATA[The Olympics Torch in Space]]></XL_Title>
		<MODALITY><![CDATA[Listening]]></MODALITY>
		<LEVEL><![CDATA[2]]></LEVEL>
		<TOPIC><![CDATA[Science]]></TOPIC>
		<TOPICs1><![CDATA[Communication and Space]]></TOPICs1>
		<RES_TYPE cked="true"><![CDATA[text]]></RES_TYPE>
		<RES_TYPE cked="true"><![CDATA[audio]]></RES_TYPE>
		<RES_TYPE><![CDATA[video]]></RES_TYPE>
		<TEXT_MOD><![CDATA[orientational]]></TEXT_MOD>
		<TEXT_MOD cked="true"><![CDATA[instructive]]></TEXT_MOD>
		<TEXT_MOD><![CDATA[evaluative]]></TEXT_MOD>
		<TEXT_MOD><![CDATA[projective]]></TEXT_MOD>
		<COMP_BROWSER cked="true"><![CDATA[ie60]]></COMP_BROWSER>
		<COMP_BROWSER cked="true"><![CDATA[nn70]]></COMP_BROWSER>
	</QREC>
	<QREC on="1">
		<A_Type><![CDATA[LMF]]></A_Type>
		<UPDATED><![CDATA[Dec 31]]></UPDATED>
		<DEV_COMMENT dir="ltr" esbox="0"><![CDATA[OK]]></DEV_COMMENT>
		<ACTY_DESCRIPTION dir="ltr" esbox="0"><![CDATA[Preview essential vocabulary to facilitate further listening.]]></ACTY_DESCRIPTION>
		<POP_UP dir="ltr" esbox="0"><![CDATA[]]>
		</POP_UP>
		<NOTE dir="ltr" esbox="0"><![CDATA[<P align=left>This lesson is best done in combination with the listening lesson <STRONG>Эстафета Олимпийского огня «Сочи - 2014» продолжается</STRONG> (find the link in the Resources), which could help you build up vocabulary on the topic of Winter Olympics that you will encounter in the upcoming audios. Put the cursor on the image to see the key words in Russian. </P>
<P align=left>
<TABLE style="BORDER-COLLAPSE: collapse" border=0 borderColor=#111111 width="100%" autocol="1">
<TBODY>
<TR>
<TD width="33%">
<P align=center><IMG title="Международная космическая станция" border=0 hspace=0 alt="Международная космическая станция" align=middle src="Images/International_Space_Station_after_undocking.gif" _src="Images/International_Space_Station_after_undocking.gif"></P></TD>
<TD width="33%">
<P align=center><IMG title="Символ олимпийских игр" border=0 hspace=0 alt="Символ олимпийских игр" align=middle src="Images/Rings.jpg" _src="Images/Rings.jpg"></P></TD>
<TD width="34%">
<P align=center><IMG title="Космический корабль" border=0 hspace=0 alt="Космический корабль" align=middle src="Images/Soyuz_TMA-7_spacecraft.gif" _src="Images/Soyuz_TMA-7_spacecraft.gif"></P></TD></TR></TBODY></TABLE></P>
<P align=center></P>
<P align=center></P>]]></NOTE>
		<FL_INST dir="ltr" esbox="0"><![CDATA[Сначала прослушайте подсказки в <STRONG>Audio Hints</STRONG>. Потом прослушайте фразы на русском языке в левой колонке и найдите их английский перевод в правой колонке.]]></FL_INST>
		<XL_INST dir="ltr" esbox="0"><![CDATA[First listen to <STRONG>Audio Hints</STRONG>. Then, listen to phrases in Russian on the left and find their English equivalents on the right.]]></XL_INST>
		<PREP_TEXT dir="ltr" esbox="0"><![CDATA[<P><FONT color=#0000ff><STRONG>Слова и фразы, относящиеся к теме "Полёты в космос" and "Олимпийские игры" -<EM> Words and phrases related to the topic "Space Flights" and "Olympic Games":</EM></STRONG></FONT></P>
<UL>
<LI><FONT color=#000000><STRONG><U>космический корабль</U></STRONG> - <EM>spaceship; spacecraft</EM></FONT> 
<LI><STRONG><FONT color=#000000><U>ракета - носитель</U></FONT></STRONG> - <EM>spacecraft launch vehicle</EM> 
<LI><STRONG><U>околоземная орбита</U></STRONG><EM> - near-Earth orbit</EM> 
<LI><STRONG><U>Международная космическая станция (МКС)</U></STRONG> <EM>- International Space Station</EM> (<EM>ISS</EM>) 
<LI><STRONG><U>пристыковаться</U> </STRONG>-<EM> to dock</EM> 
<LI><FONT color=#0000ff><FONT color=#000000><STRONG><U>открытый космос</U> </STRONG><EM>- open space</EM></FONT></FONT> 
<LI><STRONG><U>экипаж</U></STRONG> - <EM>crew</EM> 
<LI><STRONG><U>Олимпийские игры</U></STRONG> - <EM>Olympic Games </EM>
<LI><STRONG><U>олимпийский огонь</U></STRONG> is synonymous to <STRONG>олимпийский факел</STRONG><EM> - Olympic torch</EM> 
<LI><STRONG><U>эстафета олимпийского огня</U></STRONG> -<EM> the Olympic torch relay</EM> </LI></UL>]]></PREP_TEXT>
		<SRC_TYPE><![CDATA[nosource]]></SRC_TYPE>
		<SRC_TEXT dir="ltr" esbox="0"><![CDATA[]]>
		</SRC_TEXT>
		<SRC_TEXT dir="ltr" esbox="0"><![CDATA[]]>
		</SRC_TEXT>
		<ANS><![CDATA[0]]></ANS>
		<FB><![CDATA[1]]></FB>
		<NUM_Q dir="ltr" esbox="0"><![CDATA[5]]></NUM_Q>
		<AID><![CDATA[3]]></AID>
		<FB_FL dir="ltr" esbox="0"><![CDATA[Эстафета олимпийского огня "Сочи 2014" продолжается.]]></FB_FL>
		<RESPONSE dir="ltr" esbox="0"><![CDATA[The "Sochi-2014" Olympic torch relay goes on.]]></RESPONSE>
		<RIGHT_FB dir="ltr" esbox="0"><![CDATA[<P><STRONG><FONT color=#0000ff>Area Studies Note:</FONT></STRONG> </P>
<P><STRONG>Оргкомитет <U>«Сочи-2014»</U> представил маршрут олимпийского огня <U>для ХХII Зимних Олимпийских игр</U>: он пройдет через все регионы Российской Федерации. Эстафета передачи олимпийского огня - самая продолжительная и масштабная в истории Олимпийских игр.</STRONG> <EM><FONT color=#333333>The <U>"Sochi-2014"</U> organizing committee presented the Olympic torch route for <U>the XXII Winter Olympic Games;</U> it will go across all regions of the Russian Federation. The Olympic torch relay is the longest running and of the largest scale in the history of Olympic games. </FONT></EM></P>
<UL>
<LI><STRONG>эстафета олимпийского огня</STRONG> -<EM> the Olympic torch relay</EM> <FONT size=+0><FONT size=+0><FONT size=+0><FONT style="BACKGROUND-COLOR: #ffffff">[<FONT size=+0><STRONG>эстафета</STRONG> - <EM>relay race;</EM> <STRONG>огонь</STRONG> (n., mas.) -<EM> fire</EM>]</LI></UL>
<P></FONT></FONT></FONT></FONT></FONT></P>]]></RIGHT_FB>
		<WRONG_FB dir="ltr" esbox="0"><![CDATA[Listen to the city name associated with Winter Olympics 2014.]]></WRONG_FB>
		<FB_FL dir="ltr" esbox="0"><![CDATA[Космический корабль пристыковался к МКС.]]></FB_FL>
		<RESPONSE dir="ltr" esbox="0"><![CDATA[The spacecraft docked with the ISS.]]></RESPONSE>
		<RIGHT_FB dir="ltr" esbox="0"><![CDATA[<P><STRONG><FONT color=#0000ff>Lexical Note:</FONT></STRONG></P>
<UL>
<LI><STRONG>при<U>стык</U>овываться</STRONG> (imperf.) / <STRONG>при<U>стык</U>оваться</STRONG> (perf.) <STRONG>к + Dat. </STRONG>-<EM> to dock</EM> <EM>with</EM> 
<UL>
<LI><FONT size=+0><FONT size=+0><FONT size=+0><FONT size=+0><FONT style="BACKGROUND-COLOR: #ffffff"><STRONG>стыковка</STRONG> (n., fem.) <EM>- docking</EM></FONT></FONT></FONT></FONT></FONT></LI></UL></LI></UL>
<P><STRONG>Космический корабль пристыковался<U> к</U> Международн<U>ой</U> космическ<U>ой</U> станци<U>и</U></STRONG> <STRONG>(МКС).</STRONG>&nbsp; <STRONG><U>Стыковка</U> прошла нормально.</STRONG> </P>]]></RIGHT_FB>
		<WRONG_FB dir="ltr" esbox="0"><![CDATA[Focus on abbreviation that denotes a habitable artificial satellite in low Earth orbit.]]></WRONG_FB>
		<FB_FL dir="ltr" esbox="0"><![CDATA[Космонавты часто работают в открытом космосе.]]></FB_FL>
		<RESPONSE dir="ltr" esbox="0"><![CDATA[Astronauts often work in open space.]]></RESPONSE>
		<RIGHT_FB dir="ltr" esbox="0"><![CDATA[<P><STRONG><FONT color=#0000ff>Lexical Note:</FONT></STRONG></P>
<UL>
<LI><STRONG>выходить в открытый космос / работать в открытом космосе </STRONG></LI></UL>
<P>Первая сцена фильма "Гравитация" показывает как американские астронавты работают в открытом космосе.</P>]]></RIGHT_FB>
		<WRONG_FB dir="ltr" esbox="0"><![CDATA[What expression in Russian relates to space walks?]]></WRONG_FB>
		<FB_FL dir="ltr" esbox="0"><![CDATA[Ракета-носитель с экипажем на борту отправилась на околоземную орбиту.]]></FB_FL>
		<RESPONSE dir="ltr" esbox="0"><![CDATA[The spacecraft with crew members on board flew into the near-Earth orbit.]]></RESPONSE>
		<RIGHT_FB dir="ltr" esbox="0"><![CDATA[<P><STRONG><FONT color=#0000ff>Lexical Note:</FONT></STRONG></P>
<UL>
<LI><STRONG><U>ракета</U>-носитель</STRONG> - <EM>spacecraft launch vehicle</EM>&nbsp; [<STRONG>носитель</STRONG> (n., mas., tech term) -<EM> carrier,</EM> derives from <STRONG>носить</STRONG>] 
<LI><STRONG>с экипажем на борту</STRONG> - <EM>with crew members on board</EM> [<STRONG>экипаж</STRONG> (n., mas.) -<EM> crew</EM>] 
<LI><STRONG>отправиться на околоземную <U>орбиту</U></STRONG> <EM>- to depart to the near-Earth</EM> <EM>orbit </EM>[<STRONG>околоземный</STRONG> consists of two roots<STRONG> около + Земля</STRONG>] 
<UL>
<LI><FONT size=+0><FONT style="BACKGROUND-COLOR: #ffffff"><STRONG>отправиться на орбиту</STRONG> -<EM> to fly into orbit</EM> [<STRONG>отправляться</STRONG> (imperf.) / <STRONG>отправиться</STRONG> (perf.) - <EM>to depart</EM>] </FONT></FONT>
<LI><FONT size=+0><FONT style="BACKGROUND-COLOR: #ffffff"><STRONG>выходить на орбиту</STRONG> - <EM>to go into orbit </EM></FONT></FONT>
<LI><FONT size=+0><FONT style="BACKGROUND-COLOR: #ffffff"><STRONG>побывать на орбите</STRONG> - <EM>to spend time in orbit</EM> [<STRONG>побывать</STRONG> - <EM>to visit,</EM> <EM>to spend some time;</EM> derives from <STRONG>быть</STRONG> - <EM>to be</EM>]</FONT></FONT></LI></UL></LI></UL>]]></RIGHT_FB>
		<WRONG_FB dir="ltr" esbox="0"><![CDATA[Concentrate on two cognates that refer to space.]]></WRONG_FB>
		<FB_FL dir="ltr" esbox="0"><![CDATA[Олимпийский факел доставили в Россию из Греции.]]></FB_FL>
		<RESPONSE dir="ltr" esbox="0"><![CDATA[The Olympic torch was delivered from Greece to Russia.]]></RESPONSE>
		<RIGHT_FB dir="ltr" esbox="0"><![CDATA[<P><STRONG><FONT color=#0000ff>Lexical Note:</FONT></STRONG></P>
<P><STRONG>Олимпийский факел доставили в Россию из Греции</STRONG>.<EM> The Olympic torch was delivered from Greece to Russia.</EM></P>
<UL>
<LI><STRONG>факел</STRONG> (n., mas.) - <EM>torch</EM> 
<LI><STRONG>доставлять</STRONG> (imperf.)<STRONG> / доставить</STRONG> (perf.) <STRONG>из+ Gen. в + Acc. </STRONG>- <EM>to deliver from... to...</EM></LI></UL>
<P><EM></EM></P>]]></RIGHT_FB>
		<WRONG_FB dir="ltr" esbox="0"><![CDATA[Pay attention to country names associated with Olympic Games.]]></WRONG_FB>
		<SRC_AUD><![CDATA[SELECT]]></SRC_AUD>
		<AUD_STIMULUS><![CDATA[1_1.mp3]]></AUD_STIMULUS>
		<AUD_STIMULUS><![CDATA[1_2.mp3]]></AUD_STIMULUS>
		<AUD_STIMULUS><![CDATA[1_3.mp3]]></AUD_STIMULUS>
		<AUD_STIMULUS><![CDATA[1_4.mp3]]></AUD_STIMULUS>
		<AUD_STIMULUS><![CDATA[1_5.mp3]]></AUD_STIMULUS>
		<PREP_AUD><![CDATA[space ship.mp3]]></PREP_AUD>
		<PREP_AUD><![CDATA[carrier.mp3]]></PREP_AUD>
		<PREP_AUD><![CDATA[orbit.mp3]]></PREP_AUD>
		<PREP_AUD><![CDATA[ISS.mp3]]></PREP_AUD>
		<PREP_AUD><![CDATA[dock.mp3]]></PREP_AUD>
		<PREP_AUD><![CDATA[open space.mp3]]></PREP_AUD>
		<PREP_AUD><![CDATA[Crew_1.mp3]]></PREP_AUD>
		<PREP_AUD><![CDATA[Olympic Games.mp3]]></PREP_AUD>
		<PREP_AUD><![CDATA[fire_torch.mp3]]></PREP_AUD>
		<PREP_AUD><![CDATA[relay.mp3]]></PREP_AUD>
	</QREC>
	<QREC on="1">
		<A_Type><![CDATA[LGP]]></A_Type>
		<UPDATED><![CDATA[Dec 18]]></UPDATED>
		<DEV_COMMENT dir="ltr" esbox="0"><![CDATA[OK]]></DEV_COMMENT>
		<ACTY_DESCRIPTION dir="ltr" esbox="0"><![CDATA[Write a gist of the introductory part to familiarize yourself with the general content of the report.]]></ACTY_DESCRIPTION>
		<POP_UP dir="ltr" esbox="0"><![CDATA[<P><STRONG><FONT color=#0000ff>Area Studies Note:</FONT></STRONG></P>
<P><STRONG>The International Space Station (ISS)</STRONG> is a habitable artificial satellite in low Earth orbit. The ISS is a modular structure whose first component was launched in 1998. The ISS is arguably the most expensive single item ever constructed, and its existence and operation is a result of one of the most significant instances of international cooperation in modern history. The ISS serves as a microgravity and space environment research laboratory in which crew members conduct experiments in biology, human biology, physics, astronomy, meteorology and other fields. It has been visited by astronauts and cosmonauts from 15 different nations. The ISS program is a joint project among five participating space agencies: NASA, the Russian Federal Space Agency, JAXA (Japan), ESA (European Space Agency), and CSA (Canadian Space Agency). The ownership and use of the space station is established by intergovernmental treaties and agreements. The station is divided into two sections, the Russian orbital segment (ROS) and the United States orbital segment (USOS), which is shared by many nations. The ISS is maintained at an orbital altitude of between 330 km (205 mi) and 435 km (270 mi). It completes 15.7 orbits per day. The ISS is funded until 2020, and may operate until 2028. </P>]]></POP_UP>
		<NOTE dir="ltr" esbox="0"><![CDATA[]]>
		</NOTE>
		<FL_INST dir="ltr" esbox="0"><![CDATA[<P>Прослушайте начало репортажа. Следуя вспомогательной информации в <STRONG>Guidelines</STRONG>, напечатайте короткий пересказ этой части репортажа по-английски. Сверьте ваш ответ с ответом учителя (<STRONG>Compare</STRONG>) и посмотрите<STRONG> View Transcript</STRONG>. </P>
<P>Прочитайте страноведческую справку в заметке учителя <STRONG>TN</STRONG> <IMG title="" border=0 hspace=0 alt="" align=absBottom src="Images/teacherBtnSmall.gif" _src="Images/teacherBtnSmall.gif"> . </P>]]></FL_INST>
		<XL_INST dir="ltr" esbox="0"><![CDATA[<P>Listen to the beginning part of the report. Follow the additional information in the <STRONG>Guidelines</STRONG> and write a gist of the part in English in the space provided. Compare your answer to that suggested by the teacher (<STRONG>Compare</STRONG>) and see<STRONG> View Transcript</STRONG>. </P>
<P>Read Area Studies Note in the <STRONG>Teacher's Note</STRONG> <IMG title="" border=0 hspace=0 alt="" align=absMiddle src="Images/teacherBtnSmall.gif" _src="Images/teacherBtnSmall.gif"> . </P>]]></XL_INST>
		<PREP_TEXT dir="ltr" esbox="0"><![CDATA[]]>
		</PREP_TEXT>
		<QText dir="ltr" esbox="0"><![CDATA[<P>В студии Григорий Шабанов и сегодня в нашем выпуске: </P>
<P>Олимпийский огонь светит из космоса. Ракета-носитель с факелом на борту отправилась на околоземную орбиту. </P>
<P>Впервые за всю историю эстафета олимпийского огня достигла космических масштабов. Несколько часов назад ракета-носитель “Союз” с факелом на борту пристыковалась к международной космической станции. Впереди ещё один важный пункт – вынос факела в безвоздушное пространство. </P>]]></QText>
		<AID dir="ltr" esbox="0"><![CDATA[<P>There are three main bits of information in the introductory part of this clip: </P>
<OL>
<LI>The itinerary of the next leg of the Olympic torch relay. 
<LI>The means of transportation which will carry the Olympic flame. 
<LI>The most important undertaking of this stage of the relay.</LI></OL>
<P><STRONG><FONT color=#0000ff>Pay attention to expressions such as:</FONT></STRONG> </P>
<UL>
<LI><STRONG>достичь космических масштабов</STRONG> 
<LI><STRONG>важный пункт</STRONG> 
<LI><STRONG>безвоздушное пространство</STRONG></LI></UL>]]></AID>
		<STIMULUS dir="ltr" esbox="0"><![CDATA[<IMG title="Олимпийский факел" border=0 hspace=5 alt="Олимпийский факел" align=left src="Images/Torch_2a.jpg" _src="Images/Torch_2a.jpg">1. The Olympic torch relay continued into space. 
<P></P>
<P>2. The Olympic flame was launched into space on board of a spacecraft.</P>
<P>3. The ISS crewmembers will conduct a space walk with the torch.</P>
<P></P>]]></STIMULUS>
		<FB dir="ltr" esbox="0"><![CDATA[<P>The itinerary and the means of transportation were mentioned here twice—in the broadcaster Grigoriy Shabanov's announcement and in the first paragraph of the news report. The ultimate goal of the relay stage is stated in the last sentence of the audio clip.</P>
<P><STRONG><FONT color=#0000ff>Transcript:</FONT></STRONG> </P>
<P><STRONG>В студии Григорий Шабанов, и сегодня в нашем выпуске: </STRONG></P>
<P><STRONG><U>Олимпийский огонь светит из космоса. Ракета-носитель с факелом на борту отправилась на околоземную орбиту.</U> </STRONG></P>
<P><STRONG>Впервые за всю историю эстафета олимпийского огня достигла космических масштабов. Несколько часов назад <U>ракета-носитель “Союз” с факелом на борту пристыковалась к международной космической станции. Впереди ещё один важный пункт – вынос факела в безвоздушное пространство. </U></STRONG></P>
<P><EM>This is Grigoryi Shabanov, and the topic of our broadcast today is: </EM></P>
<P><EM><U>the Olympic flame shines from space.</U></EM><EM><U>The spacecraft with the torch onboard blasted off into the near-Earth orbit</U>. </EM></P>
<P><EM>The Olympic torch relay is conducted on a such large scale for the first time in history. <U>The spacecraft Soyuz with the torch onboard docked with the International Space Station several hours ago. There is one more important step ahead — to carry the torch into open space</U>.</EM></P>
<P></P>
<P></P>
<P></P>
<P></P>
<P><STRONG><FONT color=#0000ff>Lexical Note:</FONT></STRONG> </P>
<UL>
<LI><STRONG>студия</STRONG> (n., fem.) -<EM> radio studio</EM> 
<LI><STRONG>выпуск [новостей]</STRONG> - <EM>newscast</EM> 
<LI><STRONG>светить</STRONG> (imperf.) -<EM> to shine</EM> [the root is <STRONG>свет</STRONG>-<EM> light</EM>] 
<LI><STRONG>впервые за всю историю </STRONG>(set phrase) - <EM>for the first time in history</EM> 
<LI><STRONG>достичь космических масштабов</STRONG> - fig.<EM> to be of a large scale</EM> [<STRONG>достичь</STRONG> <EM>- to reach, to achieve; </EM><STRONG>масштаб</STRONG> - <EM>scale</EM>] 
<LI><STRONG>важный пункт</STRONG> (set phrase) - <EM>important point, item (in a document)</EM> 
<LI><STRONG>вынос</STRONG> (n., mas.) - <EM>carrying out</EM> [the root is <STRONG>нос-/ носить</STRONG> -<EM> to carry</EM>] 
<LI><STRONG>безвоздушное пространство</STRONG> (term) -<EM> vacuum</EM> [<STRONG>безвоздушное</STRONG> - the root is <STRONG>воздуш- / воздух</STRONG> <EM>- air; </EM><STRONG>пространство</STRONG> (n., neut.) - <EM>space</EM>] 
<UL>
<LI><STRONG>водное пространство</STRONG> - <EM>body of water</EM></LI></UL></LI></UL>]]></FB>
		<AUD_FB><![CDATA[1.mp3]]></AUD_FB>
		<AUD_STIMULUS><![CDATA[ru_sci214_act2_seg1.mp3]]></AUD_STIMULUS>
		<AUD_STIMULUS><![CDATA[SELECT]]></AUD_STIMULUS>
		<PREP_AUD><![CDATA[SELECT]]></PREP_AUD>
	</QREC>
	<QREC on="1">
		<A_Type><![CDATA[LMH]]></A_Type>
		<UPDATED><![CDATA[Dec 18]]></UPDATED>
		<DEV_COMMENT dir="ltr" esbox="0"><![CDATA[OK]]></DEV_COMMENT>
		<ACTY_DESCRIPTION dir="ltr" esbox="0"><![CDATA[Learn more details about the topic.]]></ACTY_DESCRIPTION>
		<POP_UP dir="ltr" esbox="0"><![CDATA[]]>
		</POP_UP>
		<NOTE dir="ltr" esbox="0"><![CDATA[]]>
		</NOTE>
		<FL_INST dir="ltr" esbox="0"><![CDATA[Прослушайте следующий аудио клип репортажа и отметьте все утверждения, которые правильно отражают его содержание. В этом задании три страницы.]]></FL_INST>
		<XL_INST dir="ltr" esbox="0"><![CDATA[Listen to the next clip of the report and mark all the statements that correctly reflect its content. There are three pages in this activity.]]></XL_INST>
		<PREP_TEXT dir="ltr" esbox="0"><![CDATA[]]>
		</PREP_TEXT>
		<QText dir="ltr" esbox="0"><![CDATA[2. Мария Болявина следит за необычным путешествием главного символа Олимпийских игр. 
<P></P>
<P>Корабль “Союз ТМА-11М” пристыковался к МКС в автоматическом режиме через 6 часов после старта. На околоземную орбиту Олимпийский факел доставил интернациональный экипаж длительной экспедиции: космонавт Роскосмоса Михаил Тюрин, астронавт японского космического агенства Каичи Баката и астронавт НАСА Ричард Мастракио. После стыковки космонавты должны проверить герметичность стыковочного узла. </P>]]></QText>
		<STIMULUS dir="ltr" esbox="0"><![CDATA[1. How did the spaceship dock with the International Space Station?]]></STIMULUS>
		<AID dir="ltr" esbox="0"><![CDATA[Look for cognates.]]></AID>
		<AUD_QUESTION itemNo="0"><![CDATA[SELECT]]></AUD_QUESTION>
		<RESPONSE dir="ltr" itemNo="0" esbox="0"><![CDATA[via manual docking]]></RESPONSE>
		<FB dir="ltr" itemNo="0" esbox="0"><![CDATA[<P>Incorrect. </P>
<P><STRONG>стыковка в ручном режиме</STRONG> - <EM>manual docking</EM> was not used in this case</P>]]></FB>
		<AUD_FB itemNo="0"><![CDATA[SELECT]]></AUD_FB>
		<RESPONSE dir="ltr" esbox="0" itemNo="0" crrt="true"><![CDATA[via mechanical docking]]></RESPONSE>
		<FB dir="ltr" itemNo="0" esbox="0"><![CDATA[<P>Correct.</P>
<P><STRONG>Корабль “Союз ТМА-11М” пристыковался к МКС <U>в автоматическом режиме</U> через 6 часов после старта. </STRONG><EM>Spaceship Soyuz TMA-11M docked with the ISS<U> via mechanical docking</U> six hours after the launch.</EM></P>
<P><FONT color=#0000ff><STRONG>Lexical Note:</STRONG></FONT> </P>
<UL>
<LI><STRONG>в автоматическом режиме</STRONG> is the antonym of <STRONG>в ручном режиме</STRONG> </LI></UL>]]></FB>
		<AUD_FB itemNo="0"><![CDATA[SELECT]]></AUD_FB>
		<STIMULUS dir="ltr" esbox="0"><![CDATA[2. Who delivered the Olympic torch to the orbiting outpost?]]></STIMULUS>
		<AID dir="ltr" esbox="0"><![CDATA[Listen to astronauts' names.]]></AID>
		<AUD_QUESTION itemNo="1"><![CDATA[SELECT]]></AUD_QUESTION>
		<RESPONSE dir="ltr" itemNo="1" esbox="0"><![CDATA[Russian cosmonauts]]></RESPONSE>
		<FB dir="ltr" itemNo="1" esbox="0"><![CDATA[<P>Incorrect. </P>
<P><STRONG>космонавт Роскосмоса* Михаил Тюрин</STRONG> was one of the members of the crew</P>*<STRONG>Роскосмос</STRONG> - abbr. for <STRONG>Федеральное космическое агентство России</STRONG> <EM>/ the Russian Federal Space Agency</EM> is the government agency responsible for the Russian space science program and general aerospace research]]></FB>
		<AUD_FB itemNo="1"><![CDATA[SELECT]]></AUD_FB>
		<RESPONSE dir="ltr" esbox="0" itemNo="1" crrt="true"><![CDATA[multinational crew]]></RESPONSE>
		<FB dir="ltr" itemNo="1" esbox="0"><![CDATA[<P>Correct. </P>
<P><STRONG><IMG title="Интернациональный экипаж" border=0 hspace=5 alt="Интернациональный экипаж" align=baseline src="Images/Int crew.jpg" _src="Images/Int crew.jpg"></STRONG></P>
<P><STRONG>На околоземную орбиту Олимпийский факел доставил <U>интернациональный экипаж</U> длительной экспедиции: <U>космонавт Роскосмоса Михаил Тюрин, астронавт японского космического агенства Каичи Баката и астронавт НАСА Ричард Мастракио.</U></STRONG> <EM>The Olympic torch was delivered to the near-Earth orbit <U>by a multunational crew</U> of the long term space mission: <U>Mikhail Tyurin (Roscosmos), Koici Wakata (Japan's JAXA) and&nbsp; Rick Mastracchio (NASA</U>).</EM></P>
<P><STRONG><FONT color=#0000ff>Lexical / Syntactical Note:</FONT></STRONG></P>
<UL>
<LI><STRONG>экипаж длительной экспедиции</STRONG> (term) - <EM>long term space mission</EM> [<STRONG>длительный</STRONG> (adj.) - derives from <STRONG>длина</STRONG> - <EM>length</EM>] 
<LI>The reversed sentence word order is common for Russian syntax (here the subject <STRONG>экипаж длительной экспедиции </STRONG>is in the middle of the sentence) when something is emphasized in the phrase.</LI></UL>]]></FB>
		<AUD_FB itemNo="1"><![CDATA[SELECT]]></AUD_FB>
		<STIMULUS dir="ltr" esbox="0"><![CDATA[3. What should astronauts check after docking with the ISS?]]></STIMULUS>
		<AID dir="ltr" esbox="0"><![CDATA[Look for technical terms.]]></AID>
		<AUD_QUESTION itemNo="2"><![CDATA[SELECT]]></AUD_QUESTION>
		<RESPONSE dir="ltr" esbox="0" itemNo="2" crrt="true"><![CDATA[the hermetic sealing of the systems]]></RESPONSE>
		<FB dir="ltr" itemNo="2" esbox="0"><![CDATA[<P>Correct. </P>
<P><STRONG dir=ltr>После стыковки космонавты должны проверить <U>герметичность</U> стыковочного узла.</STRONG> <EM>Astronauts should check <U>the hermetic sealing</U> of the docking unit after the docking.</EM></P>
<P><STRONG><FONT color=#0000ff>Lexiacl Note:</FONT></STRONG></P>
<UL>
<LI><STRONG>герметичность стыковочного узла</STRONG> (term) - <EM>hermetic sealing of the docking unit</EM> [<STRONG>герметичность</STRONG> (n., fem.) - <EM>air-tightness, hermetically sealed</EM>; <STRONG><U>стык</U>овочный узел</STRONG> - <EM>docking unit</EM>]</LI></UL>]]></FB>
		<AUD_FB itemNo="2"><![CDATA[SELECT]]></AUD_FB>
		<RESPONSE dir="ltr" itemNo="2" esbox="0"><![CDATA[whether communication with Mission Control works]]></RESPONSE>
		<FB dir="ltr" itemNo="2" esbox="0"><![CDATA[<P>Incorrect. </P>
<P><STRONG>есть ли <U>связь</U> с Центром управления полетов</STRONG> - <EM>whether <U>communication</U> with Mission Control is in effect</EM> was not mentioned here</P>]]></FB>
		<AUD_FB itemNo="2"><![CDATA[SELECT]]></AUD_FB>
		<AUD_STIMULUS itemNo=""><![CDATA[ru_sci214_act3_all.mp3]]></AUD_STIMULUS>
		<AUD_STIMULUS itemNo=""><![CDATA[SELECT]]></AUD_STIMULUS>
		<PREP_AUD itemNo=""><![CDATA[SELECT]]></PREP_AUD>
	</QREC>
	<QREC on="1">
		<A_Type><![CDATA[LBS]]></A_Type>
		<UPDATED><![CDATA[Dec 31]]></UPDATED>
		<DEV_COMMENT dir="ltr" esbox="0"><![CDATA[OK]]></DEV_COMMENT>
		<ACTY_DESCRIPTION dir="ltr" esbox="0"><![CDATA[Identify essential elements of information within audio segments.]]></ACTY_DESCRIPTION>
		<POP_UP dir="ltr" esbox="0"><![CDATA[На МКС вновь прибывший экипаж присоединится к тем космонавтам, которые уже находятся на станции: россиянам Олегу Котову, Сергею Рязанскому, Фёдору Юрчихину, американцам Майклу Хопкинсу и Карен Найберг, а также к итальянцу Луке Парметано. На орбитальной станции будут находиться сразу 9 космонавтов и 3 пристыкованных корабля. Напомним, “Союз” с олимпийским огнем стартовал с первой площадки космодрома Байконур, откуда отправлялся в космос Юрий Гагарин. В 8 часов 23 минуты по московскому времени космический корабль вышел на орбиту дальнего сближения с МКС – доложил Земле капитан/командир корабля Михаил Тюрин. Этот полёт – знаменательное событие не только в истории российской космонавтики, но и в истории всего олимпийского движения. На МКС эстафету приняли российские космонавты Олег Котов и Сергей Рязанский, которые 9 ноября выйдут с факелом в открытый космос. Зажигать на станции его не будут из соображений безопасности. 11 ноября экипаж в составе россиянина Фёдора Юрчихина, американки Карен Найберг и итальянца Луки Парметано доставит олимпийский факел на Землю. Именно от него зажгут Олимпийский огонь на церемонии открытия игр в Сочи.]]></POP_UP>
		<NOTE dir="ltr" esbox="0"><![CDATA[На околоземную орбиту Олимпийский факел доставил интернациональный экипаж длительной экспедиции: космонавт Роскосмоса Михаил Тюрин, астронавт японского космического агенства Каичи Баката и астронавт НАСА Ричард Мастракио.]]></NOTE>
		<FL_INST dir="ltr" esbox="0"><![CDATA[Прослушайте весь репортаж (<STRONG>Whole Passage</STRONG>). Ознакомьтесь с подсказками в <STRONG>Audio Hints</STRONG>.) Сначала прочитайте информацию в верхней части страницы. Затем прослушайте репортаж по частям и ответьте на вопросы, напечатав ваши ответы по-английски в окошках справа. В этом задании две страницы. Ознакомьтесь с текстом в заметке учителя <IMG title="" border=0 hspace=0 alt="" align=absBottom src="Images/teacherBtnSmall.gif" _src="Images/teacherBtnSmall.gif"><STRONG>.</STRONG>]]></FL_INST>
		<XL_INST dir="ltr" esbox="0"><![CDATA[Click on <STRONG>Whole Passage</STRONG> to listen to the entire audio. Open the <STRONG>Audio Hints </STRONG>to preview some key vocabulary. Read the note at the top of the page before you begin the activity. Listen to short audio segments and write your answers in English in the spaces on the right. There are two pages in this activity. You can see <STRONG>Transcript </STRONG>in the <STRONG>Teacher's Note <IMG title="" border=0 hspace=0 alt="" align=absBottom src="Images/teacherBtnSmall.gif" _src="Images/teacherBtnSmall.gif">.</STRONG>]]></XL_INST>
		<PREP_TEXT dir="ltr" esbox="0"><![CDATA[<P><STRONG><FONT color=#0000ff>Pay attention to the following phrases:</FONT></STRONG> </P>
<UL>
<LI><STRONG><U>вновь прибывший экипаж</U></STRONG> -<EM> newly arrived crew</EM> 
<LI><STRONG><U>экипаж в составе...</U></STRONG> -<EM> the crew consisting of</EM> 
<LI><STRONG><U>площадка космодрома</U></STRONG><EM> - launch pad</EM> 
<LI><STRONG><U>орбита дальнего сближения</U> </STRONG><EM>- rendezvous orbit </EM>
<LI><STRONG><U>знаменательное событие</U></STRONG> - <EM>memorable event</EM> 
<LI><STRONG><U>олимпийское движение</U></STRONG> - <EM>Olympic movement</EM> 
<LI><STRONG><U>принять эстафету</U> </STRONG>-<EM> to take up relay</EM> 
<LI><U><STRONG>зажигать</STRONG> </U><EM>- to light, to turn on the light</EM> 
<LI><STRONG><U>из соображений безопасности</U></STRONG><EM> -</EM> <EM>for reasons of safety</EM></LI></UL>]]></PREP_TEXT>
		<AID><![CDATA[wholeAudio]]></AID>
		<NUM_Q><![CDATA[3]]></NUM_Q>
		<STIMULUS dir="ltr" esbox="0"><![CDATA[]]>
		</STIMULUS>
		<AUD_STIMULUS><![CDATA[ru_sci214_act4_seg1.mp3]]></AUD_STIMULUS>
		<RESPONSE dir="ltr" esbox="0" segNo="0"><![CDATA[<P>1. What was the new composition of the ISS crew upon the arrival of the torch-carrying members?</P>]]></RESPONSE>
		<FB dir="ltr" esbox="0" segNo="0"><![CDATA[<P>Altogether, the orbiting station hosted nine astronauts (four Russians, three Americans, one Italian, and one Japanese) and three docked spaceships.</P>
<P><STRONG><FONT color=#0000ff>Transcript:</FONT></STRONG></P>
<P><STRONG>На МКС вновь прибывший экипаж присоединится к тем космонавтам, которые уже находятся на станции: россиянам Олегу Котову, Сергею Рязанскому, Фёдору Юрчихину, американцам Майклу Хопкинсу и Карен Найберг, а также к итальянцу Луке Пармитано. <U>На орбитальной станции будут находиться сразу 9 космонавтов и 3 пристыкованных корабля</U></STRONG>. <EM>The newly arrived crew will join the ISS crewmembers who have been stationed there: Russians Oleg Kotov, Sergei Ryazansky, and Fyodor Yurchikhin, Americans Michael Hopkins and Karen Nyberg, as well as Italian Luca Parmitano. <U>Simultaneously there will be nine cosmonauts and three docked spaceships at the orbiting station.</U></EM></P>
<P><STRONG><FONT color=#0000ff>Lexical Note:</FONT></STRONG></P>
<UL>
<LI><STRONG>вновь прибывший</STRONG> <EM>- newly arrived</EM> [<STRONG>вновь</STRONG> (adv.) - <EM>newly; </EM><STRONG>прибывший</STRONG>&nbsp; (past active participle from <STRONG>прибыть</STRONG> - <EM>to arrive</EM>] 
<LI><STRONG>присоединяться</STRONG> (imperf., refl.) /<STRONG> присоединиться</STRONG> (perf.) <STRONG>к + Dat. </STRONG>- <EM>to join; to be added to</EM> 
<LI><STRONG>сразу</STRONG> (adv.) - <EM>at once</EM> 
<LI><STRONG>пристыкованный</STRONG> (past passive participle from <STRONG>пристыковать</STRONG> - <EM>to dock</EM>) - <EM>docked</EM></LI></UL>
<P><FONT color=#000000><EM></EM></FONT></P>]]></FB>
		<WRONG_FB><![CDATA[SELECT]]></WRONG_FB>
		<STIMULUS dir="ltr" esbox="0"><![CDATA[]]>
		</STIMULUS>
		<AUD_STIMULUS><![CDATA[ru_sci214_act4_seg2.mp3]]></AUD_STIMULUS>
		<RESPONSE dir="ltr" esbox="0" segNo="1"><![CDATA[2. What is the historic significance of the location from which the “Soyuz” carrying the Olympic torch was launched?]]></RESPONSE>
		<FB dir="ltr" esbox="0" segNo="1"><![CDATA[<P><IMG title="Юрий Гагарин - первый в мире космонавт" border=0 hspace=0 alt="Юрий Гагарин - первый в мире космонавт" align=left src="Images/Yuri-Gagarin.gif" _src="Images/Yuri-Gagarin.gif">The launch pad number 1 is associated with the name of Yuri Gagrin, the first human in space. [<STRONG>Ю́рий Алексе́евич Гага́рин</STRONG> — советский лётчик-космонавт, Герой Советского Союза. 12 апреля 1961 года он стал первым человеком в мире, который полетел в космос.]</P>
<P><STRONG><FONT color=#0000ff>Transcript:</FONT></STRONG></P>
<P><STRONG>Напомним, “Союз” с олимпийским огнем стартовал с первой площадки космодрома Байконур, откуда отправлялся в космос Юрий Гагарин.</STRONG> <EM>Note that the Soyuz with the Olympic torch on board blasted off from the Boikonur Cosmodrome launch pad number one – the same launch pad from which Yuri Gagarin took off into space.</EM></P>
<P><STRONG><FONT color=#0000ff>Area Studies Note:</FONT></STRONG></P>
<P><EM></EM></P>
<P></P>
<P></P><IMG title='Космодром "Байконур"' border=0 hspace=0 alt='Космодром "Байконур"' align=left src="Images/-Baikonur_Cosmodrome.gif" _src="Images/-Baikonur_Cosmodrome.gif"><STRONG>The Baikonur Cosmodrome</STRONG> (<EM>космодром «Байконур»</EM>) is the world's first and largest operational space launch facility. It is located in the desert steppes of Kazakhstan. It is leased by the Kazakh government to Russia (until 2050) and is managed jointly by the Russian Federal Space Agency and the Russian Space Forces. It was originally built by the Soviet Union in the late 1950s as the base of operations for its space program. Under the current Russian space program, Baikonur remains a busy space port, with numerous commercial, military and scientific missions being launched annually. Currently, all manned Russian space flights are launched from Baikonur.]]></FB>
		<WRONG_FB><![CDATA[SELECT]]></WRONG_FB>
		<STIMULUS dir="ltr" esbox="0"><![CDATA[]]>
		</STIMULUS>
		<AUD_STIMULUS><![CDATA[ru_sci214_act4_seg3.mp3]]></AUD_STIMULUS>
		<RESPONSE dir="ltr" esbox="0" segNo="2"><![CDATA[3. What did the spaceship Commander Mikhail Tyurin report to Earth?]]></RESPONSE>
		<FB dir="ltr" esbox="0" segNo="2"><![CDATA[<P><IMG title="Командир корабля Михаил Тюрин" border=0 hspace=5 alt="Командир корабля Михаил Тюрин" align=left src="Images/Mikhail_Tyurin.jpg" _src="Images/Mikhail_Tyurin.jpg">At 8:23 a.m. Moscow time the Russian cosmonaut reported that Souyz had reached the rendezvous orbit with the ISS.</P>
<P><STRONG><FONT color=#0000ff>Transcript:</FONT></STRONG> </P>
<P></P>
<P><STRONG></STRONG></P>
<P><STRONG><U>В 8 часов 23 минуты по московскому времени космический корабль вышел на орбиту дальнего сближения с МКС</U> – доложил Земле капитан корабля Михаил Тюрин.</STRONG> <EM>The spaceship Commander Mikhail Tyurin reported back to Earth that <U>the spacecraft had reached the rendezvous orbit with the ISS at 8:23 a.m. Moscow time.</U></EM></P>
<P><STRONG><FONT color=#0000ff>Lexical Note:</FONT></STRONG></P>
<UL>
<LI><STRONG>орбита дальнего сближения с МКС</STRONG> (term) - <EM>rendezvous orbit with the ISS</EM> [<STRONG>дальний</STRONG> (adj.) - <EM>distant</EM>; <STRONG>сближение</STRONG> (n., neut.) - <EM>approach, closing in;</EM> the root is <STRONG>ближ- / близкий</STRONG>] 
<LI><STRONG>докладывать</STRONG> (imperf.) /<STRONG> доложить</STRONG> (perf.) -<EM> to report</EM></LI></UL>]]></FB>
		<WRONG_FB><![CDATA[SELECT]]></WRONG_FB>
		<STIMULUS dir="ltr" esbox="0"><![CDATA[]]>
		</STIMULUS>
		<AUD_STIMULUS><![CDATA[ru_sci214_act4._seg4.mp3]]></AUD_STIMULUS>
		<RESPONSE dir="ltr" esbox="0" segNo="3"><![CDATA[4. How is the present Olympic torch’ journey into space different from such events in the past?]]></RESPONSE>
		<FB dir="ltr" esbox="0" segNo="3"><![CDATA[<P>Because two Russian astronauts will take the torch on a space walk [the Olympic torch has been carried into space twice before - in 1996 and 2000 - but it has never left a spaceship.] </P>
<P><STRONG><FONT color=#0000ff>Transcript:</FONT></STRONG></P>
<P><STRONG><U>Этот полёт</U> – <U>знаменательное событие не только в истории российской космонавтики, но и в истории всего олимпийского движения.</U> На МКС эстафету приняли российские космонавты <U>Олег Котов и Сергей Рязанский, которые 9 ноября выйдут с факелом в открытый космос.</U></STRONG> <EM><U>This flight is a memorable event not only in the history of the Russian space science, but also in the history of the entire Olympic movement.</U> The torch has been taken up by Russian cosmonauts <U>Oleg Kotov and Sergei Ryazansky who will take it on a space walk on November 9.</U></EM></P>
<P></P>
<P></P>
<P><STRONG><FONT color=#0000ff>Lexical Note:</FONT></STRONG> </P>
<UL>
<LI><STRONG>знаменательное событие</STRONG> - <EM>memorable event </EM>[<STRONG>знаменательный</STRONG> (adj.) - <EM>remarkable, outstanding, memorable, significant; </EM><STRONG>событие</STRONG> (n., neut.) - <EM>event</EM>] 
<LI><STRONG>космонавтика</STRONG><EM> - space science</EM> 
<LI><STRONG>олимпийское&nbsp; движение</STRONG> <EM>- Olympic movement</EM> [<STRONG>движение</STRONG> (n., neut.) - <EM>movement, motion, traffic</EM>] 
<LI><STRONG>принимать</STRONG> (imperf.) /<STRONG> принять эстафету</STRONG> (perf.) - <EM>to take up relay</EM> 
<LI><STRONG>выходить</STRONG> (imperf.) /<STRONG> выйти</STRONG> (perf.) <STRONG>в открытый космос </STRONG>- <EM>to go on a spacewalk</EM></LI></UL>]]></FB>
		<WRONG_FB><![CDATA[SELECT]]></WRONG_FB>
		<STIMULUS dir="ltr" esbox="0"><![CDATA[]]>
		</STIMULUS>
		<AUD_STIMULUS><![CDATA[ru_sci214_act4_seg5.mp3]]></AUD_STIMULUS>
		<RESPONSE dir="ltr" esbox="0" segNo="4"><![CDATA[5. What safety measure concerning the Olympic torch space-carrying journey was mentioned in the report?]]></RESPONSE>
		<FB dir="ltr" esbox="0" segNo="4"><![CDATA[<P>The lighting of the torch aboard the ISS.</P>
<P><STRONG><FONT color=#0000ff>Transcript:</FONT></STRONG></P>
<P><STRONG>Зажигать на станции его не будут из соображений безопасности.</STRONG> -<STRONG> </STRONG><EM>The torch won't be lit inside the ISS because of safety concerns [and outside due to the lack of an oxygen system</EM>.]</P>
<P><STRONG><FONT color=#0000ff>Lexical Note:</FONT></STRONG></P>
<P></P>
<UL>
<LI><STRONG>зажигать </STRONG>(imperf.) / <STRONG>зажечь</STRONG> (perf.) - <EM>to light, to turn on a light, to fire up</EM> 
<LI><STRONG>из соображений безопасности</STRONG><EM> - for reasons of safety; because of safety concerns</EM> [<STRONG>соображение</STRONG> (n. neut.) - <EM>consideration, reason; </EM><STRONG>безопасность</STRONG> (n. fem.) - <EM>safety, security; </EM><STRONG>опасность</STRONG> <EM>- danger</EM>]</LI></UL>
<P></P>]]></FB>
		<WRONG_FB><![CDATA[SELECT]]></WRONG_FB>
		<STIMULUS dir="ltr" esbox="0"><![CDATA[]]>
		</STIMULUS>
		<AUD_STIMULUS><![CDATA[ru_sci214_act4_seg6.mp3]]></AUD_STIMULUS>
		<RESPONSE dir="ltr" esbox="0" segNo="5"><![CDATA[6. What will be the final mission of the Olympic torch?]]></RESPONSE>
		<FB dir="ltr" esbox="0" segNo="5"><![CDATA[<IMG title="Церемония открытия Олимпийских игр" border=0 hspace=5 alt="Церемония открытия Олимпийских игр" align=left src="Images/Olympics_opening_gala.jpg" _src="Images/Olympics_opening_gala.jpg">This is the torch that will be used to light the Olympic cauldron in Sochi. 
<P></P>
<P><STRONG><FONT color=#0000ff></FONT></STRONG></P>
<P><STRONG><FONT color=#0000ff>Transcript:</FONT></STRONG></P>
<P><STRONG>11 ноября <U>экипаж</U> в составе россиянина Фёдора Юрчихина, американки Карен Найберг и итальянца Луки Пармитано<U> доставит олимпийский факел на Землю. Именно от него зажгут Олимпийский огонь на церемонии открытия игр в Сочи</U></STRONG>. <EM><U>The crew</U>&nbsp; consisting of Russia's Fyodor Yurchikhin, American Karen Nyberg and Italy's Luca Parmitano <U>will deliver the torch to Earth on November 11</U>. <U>This is the torch that will be used to light the Olympic flame at the Sochi Olympics opening ceremony</U>.</EM></P>
<P><STRONG><FONT color=#0000ff>Lexical Note:</FONT></STRONG></P>
<UL>
<LI><STRONG>экипаж в составе...</STRONG> -<EM> the crew consisting of</EM> [<STRONG>в составе </STRONG>- <EM>made up of, in the composition of</EM> ] 
<LI><STRONG>именно</STRONG> (particle) -<EM> namely</EM> 
<LI><STRONG>церемония открытия игр</STRONG> <EM>- Olympic Games opening ceremony</EM></LI></UL>]]></FB>
		<WRONG_FB><![CDATA[SELECT]]></WRONG_FB>
		<AUD_QUESTION><![CDATA[ru_sci214_act4_all.mp3]]></AUD_QUESTION>
		<PREP_AUD><![CDATA[crew.mp3]]></PREP_AUD>
		<PREP_AUD><![CDATA[composition.mp3]]></PREP_AUD>
		<PREP_AUD><![CDATA[launch pad.mp3]]></PREP_AUD>
		<PREP_AUD><![CDATA[rendezvous orbit.mp3]]></PREP_AUD>
		<PREP_AUD><![CDATA[event.mp3]]></PREP_AUD>
		<PREP_AUD><![CDATA[movement.mp3]]></PREP_AUD>
		<PREP_AUD><![CDATA[take up relay.mp3]]></PREP_AUD>
		<PREP_AUD><![CDATA[to light.mp3]]></PREP_AUD>
		<PREP_AUD><![CDATA[safety.mp3]]></PREP_AUD>
	</QREC>
	<QREC on="1">
		<A_Type><![CDATA[LGP]]></A_Type>
		<UPDATED><![CDATA[Dec 18]]></UPDATED>
		<DEV_COMMENT dir="ltr" esbox="0"><![CDATA[]]>
		</DEV_COMMENT>
		<ACTY_DESCRIPTION dir="ltr" esbox="0"><![CDATA[Practice oral expression of set phrases pertaining to space and Olympic Games.]]></ACTY_DESCRIPTION>
		<POP_UP dir="ltr" esbox="0"><![CDATA[]]>
		</POP_UP>
		<NOTE dir="ltr" esbox="0"><![CDATA[]]>
		</NOTE>
		<FL_INST dir="ltr" esbox="0"><![CDATA[Прослушайте весь репортаж. Следуйте дополнительной инструкции в <STRONG>Guidelines</STRONG>, и напечатайте короткий пересказ репортажа по-русски. Прочитайте объяснения учителя (<STRONG>Compare</STRONG>). Прочитайте ваш пересказ вслух - вы можете послушать запись пересказа, сделанную учителем.]]></FL_INST>
		<XL_INST dir="ltr" esbox="0"><![CDATA[Listen to the entire broadcast. Follow the instruction in the <STRONG>Guidelines</STRONG> to write a synopsis of the report in Russian. Read the teacher’s explanations (<STRONG>Compare</STRONG>). Practice reading your summary aloud — you can listen to the teacher's voicing as well.]]></XL_INST>
		<PREP_TEXT dir="ltr" esbox="0"><![CDATA[]]>
		</PREP_TEXT>
		<QText dir="ltr" esbox="0"><![CDATA[<P>1. В студии Григорий Шабанов и сегодня в нашем выпуске: <U>Олимпийский огонь светит из космоса. Ракета-носитель с факелом на борту отправилась на околоземную орбиту. </U></P>
<P>Впервые за всю историю эстафета олимпийского огня достигла космических масштабов. <U>Несколько часов назад ракета-носитель “Союз” с факелом на борту пристыковалась к международной космической станции.</U> Впереди ещё один важный пункт – вынос факела в безвоздушное пространство. </P>
<P>2. Мария Болявина следит за необычным путешествием главного символа Олимпийских игр. </P>
<P>Корабль “Союз ТМА-11М” пристыковался к МКС в автоматическом режиме через 6 часов после старта. <U>На околоземную орбиту Олимпийский факел доставил интернациональный экипаж длительной экспедиции: космонавт Роскосмоса Михаил Тюрин, астронавт японского космического агенства Каичи Баката и астронавт НАСА Ричард Мастракио</U>. После стыковки космонавты должны проверить герметичность стыковочного узла.</P>
<P>3. На МКС вновь прибывший экипаж присоединится к тем космонавтам, которые уже находятся на станции: россиянам Олегу Котову, Сергею Рязанскому, Фёдору Юрчихину, американцам Майклу Хопкинсу и Карен Найберг, а также к итальянцу Луке Парметано. На орбитальной станции будут находиться сразу 9 космонавтов и 3 пристыкованных корабля. </P>
<P>4. Напомним, “Союз” с олимпийским огнем стартовал с первой площадки космодрома Байконур, откуда отправлялся в космос Юрий Гагарин. В 8 часов 23 минуты по московскому времени космический корабль вышел на орбиту дальнего сближения с МКС – доложил Земле капитан/командир корабля Михаил Тюрин. </P>
<P>5.<U> Этот полёт – знаменательное событие не только в истории российской космонавтики, но и в истории всего олимпийского движения</U>. <U>На МКС эстафету приняли российские космонавты Олег Котов и Сергей Рязанский, которые 9 ноября выйдут с факелом в открытый космос</U>. Зажигать на станции его не будут из соображений безопастности. </P>
<P>6. 11 ноября экипаж в составе россиянина Фёдора Юрчихина, американки Карен Найберг и итальянца Луки Парметано доставит олимпийский факел на Землю. Именно от него зажгут Олимпийский огонь на церемонии открытия игр в Сочи. </P>]]></QText>
		<AID dir="ltr" esbox="0"><![CDATA[<P>Write a short summary of the report in Russian by answering the following questions: </P>
<OL>
<LI>What was the most unusual part of the Olympic torch’s journey? 
<LI>How was the Olympic torch delivered to the space station? 
<LI>What part of the Olympic torch’s space journey has been done for the first time in the history of the Olympic Games? 
<LI>When will the Olympic torch return to Earth? 
<LI>What will be the final mission of the Olympic torch? </LI></OL>]]></AID>
		<STIMULUS dir="ltr" esbox="0"><![CDATA[1. Часть пути Олимпийского факела прошла в космосе/ на борту международной космической станции / МКС.]]></STIMULUS>
		<FB dir="ltr" esbox="0"><![CDATA[<P>See Paragraph 1 in <STRONG>Transcript</STRONG>. </P>
<P><STRONG><FONT color=#0000ff>Vocabulary to retain:</FONT></STRONG></P>
<UL>
<LI><STRONG>следующий этап эстафеты олимпийского огня</STRONG> 
<LI><STRONG>отправить факел на околоземную орбиту / на Международную космическую станцию</STRONG> / <STRONG>на МКС</STRONG></LI></UL>
<P></P>]]></FB>
		<STIMULUS dir="ltr" esbox="0"><![CDATA[2. Ракета-носитель «Союз» доставила Олимпийский факел на МКС. / Экипаж ракеты-носителя: российский космонавт Михаил Тюрин, японец Каичи Баката, американский астронавт Ричард Мастракио - доставили Олимпийский факел на МКС.]]></STIMULUS>
		<FB dir="ltr" esbox="0"><![CDATA[<P>See Paragraph 1 in <STRONG>Transcript</STRONG>.</P>
<P><STRONG><FONT color=#0000ff>Vocabulary to retain:</FONT></STRONG></P>
<UL>
<LI><STRONG>ракета-носитель с факелом на борту </STRONG>
<LI><STRONG>отправиться на околоземную орбиту</STRONG> 
<LI><STRONG>доставить</STRONG> <STRONG>факел</STRONG> 
<LI><STRONG>пристыковаться к Международной космической станции </STRONG></LI></UL>
<P></P>
<P><STRONG></STRONG></P>]]></FB>
		<STIMULUS dir="ltr" esbox="0"><![CDATA[3. Два российских космонавта в первый раз в истории Олимпийских игр вынесут Олимпийский факел в открытый космос.]]></STIMULUS>
		<FB dir="ltr" esbox="0"><![CDATA[<P>See Paragraphs 1 and 5 in <STRONG>Transcript.</STRONG></P>
<P><STRONG><FONT color=#0000ff>Vocabulary to retain:</FONT></STRONG></P>
<UL>
<LI><STRONG>выйти с факелом в открытый космос / в безвоздушное пространство </STRONG></LI></UL>
<P></P>
<P><STRONG></STRONG></P>]]></FB>
		<STIMULUS dir="ltr" esbox="0"><![CDATA[4. 11 ноября экипаж в составе россиянина Фёдора Юрчихина, американки Карен Найберг и итальянца Луки Пармитано доставит факел обратно на Землю. 
<P></P>
<P></P>]]></STIMULUS>
		<FB dir="ltr" esbox="0"><![CDATA[<P>See Paragraph 6 in <STRONG>Transcript</STRONG>.</P>
<P><STRONG><FONT color=#0000ff></FONT></STRONG></P>
<P><STRONG><FONT color=#0000ff>Vocabulary to retain:</FONT></STRONG></P>
<UL>
<LI><STRONG>экипаж в составе</STRONG> </LI></UL>]]></FB>
		<STIMULUS dir="ltr" esbox="0"><![CDATA[5. На церемонии открытия Олимпийских игр в Сочи от Олимпийского факела зажгут Олимпийский огонь.]]></STIMULUS>
		<FB dir="ltr" esbox="0"><![CDATA[<P>See Paragraph 6 in <STRONG>Transcript</STRONG>.</P>
<P><STRONG><FONT color=#0000ff></FONT></STRONG></P>
<P><STRONG><FONT color=#0000ff>Vocabulary to retain:</FONT></STRONG></P>
<UL>
<LI><STRONG>на церемонии открытия Олимпийских игр</STRONG> 
<LI><STRONG>зажечь Олимпийский огонь</STRONG></LI></UL>]]></FB>
		<AUD_FB><![CDATA[1.mp3]]></AUD_FB>
		<AUD_FB><![CDATA[5_2.mp3]]></AUD_FB>
		<AUD_FB><![CDATA[5_3.mp3]]></AUD_FB>
		<AUD_FB><![CDATA[11_NOV.mp3]]></AUD_FB>
		<AUD_FB><![CDATA[5_5.mp3]]></AUD_FB>
		<AUD_STIMULUS><![CDATA[ru_sci214_Source.mp3]]></AUD_STIMULUS>
		<AUD_STIMULUS><![CDATA[SELECT]]></AUD_STIMULUS>
		<PREP_AUD><![CDATA[SELECT]]></PREP_AUD>
	</QREC>
	<QREC on="1">
		<A_Type><![CDATA[GG]]></A_Type>
		<UPDATED><![CDATA[Dec 17]]></UPDATED>
		<DEV_COMMENT dir="ltr" esbox="0"><![CDATA[OK]]></DEV_COMMENT>
		<GlosLeft dir="ltr" esbox="0"><![CDATA[огонь]]></GlosLeft>
		<GlosRight dir="ltr" esbox="0"><![CDATA[fire]]></GlosRight>
		<GlosLeft dir="ltr" esbox="0"><![CDATA[факел]]></GlosLeft>
		<GlosRight dir="ltr" esbox="0"><![CDATA[torch]]></GlosRight>
		<GlosLeft dir="ltr" esbox="0"><![CDATA[эстафета]]></GlosLeft>
		<GlosRight dir="ltr" esbox="0"><![CDATA[relay]]></GlosRight>
		<GlosLeft dir="ltr" esbox="0"><![CDATA[светить]]></GlosLeft>
		<GlosRight dir="ltr" esbox="0"><![CDATA[to shine]]></GlosRight>
		<GlosLeft dir="ltr" esbox="0"><![CDATA[достигать / достичь]]></GlosLeft>
		<GlosRight dir="ltr" esbox="0"><![CDATA[to reach]]></GlosRight>
		<GlosLeft dir="ltr" esbox="0"><![CDATA[масштаб]]></GlosLeft>
		<GlosRight dir="ltr" esbox="0"><![CDATA[scale]]></GlosRight>
		<GlosLeft dir="ltr" esbox="0"><![CDATA[пристыковываться /пристыковаться]]></GlosLeft>
		<GlosRight dir="ltr" esbox="0"><![CDATA[to dock]]></GlosRight>
		<GlosLeft dir="ltr" esbox="0"><![CDATA[стыковка]]></GlosLeft>
		<GlosRight dir="ltr" esbox="0"><![CDATA[docking]]></GlosRight>
		<GlosLeft dir="ltr" esbox="0"><![CDATA[экипаж]]></GlosLeft>
		<GlosRight dir="ltr" esbox="0"><![CDATA[crew]]></GlosRight>
		<GlosLeft dir="ltr" esbox="0"><![CDATA[присоединяться / присоединиться]]></GlosLeft>
		<GlosRight dir="ltr" esbox="0"><![CDATA[to join]]></GlosRight>
		<GlosLeft dir="ltr" esbox="0"><![CDATA[докладывать / доложить]]></GlosLeft>
		<GlosRight dir="ltr" esbox="0"><![CDATA[to report]]></GlosRight>
		<GlosLeft dir="ltr" esbox="0"><![CDATA[событие]]></GlosLeft>
		<GlosRight dir="ltr" esbox="0"><![CDATA[event]]></GlosRight>
		<GlosLeft dir="ltr" esbox="0"><![CDATA[движение]]></GlosLeft>
		<GlosRight dir="ltr" esbox="0"><![CDATA[movement]]></GlosRight>
		<GlosLeft dir="ltr" esbox="0"><![CDATA[зажигать / зажечь]]></GlosLeft>
		<GlosRight dir="ltr" esbox="0"><![CDATA[to light]]></GlosRight>
		<GlosLeft dir="ltr" esbox="0"><![CDATA[безопасность]]></GlosLeft>
		<GlosRight dir="ltr" esbox="0"><![CDATA[safety]]></GlosRight>
		<AUD_STIMULUS><![CDATA[G_fire.mp3]]></AUD_STIMULUS>
		<AUD_STIMULUS><![CDATA[Gl_torch.mp3]]></AUD_STIMULUS>
		<AUD_STIMULUS><![CDATA[GL_relay.mp3]]></AUD_STIMULUS>
		<AUD_STIMULUS><![CDATA[GL_light.mp3]]></AUD_STIMULUS>
		<AUD_STIMULUS><![CDATA[Gl_reach.mp3]]></AUD_STIMULUS>
		<AUD_STIMULUS><![CDATA[scale.mp3]]></AUD_STIMULUS>
		<AUD_STIMULUS><![CDATA[to dock.mp3]]></AUD_STIMULUS>
		<AUD_STIMULUS><![CDATA[GL_docking.mp3]]></AUD_STIMULUS>
		<AUD_STIMULUS><![CDATA[GL_crew.mp3]]></AUD_STIMULUS>
		<AUD_STIMULUS><![CDATA[GL_join.mp3]]></AUD_STIMULUS>
		<AUD_STIMULUS><![CDATA[GL_report.mp3]]></AUD_STIMULUS>
		<AUD_STIMULUS><![CDATA[GL_event.mp3]]></AUD_STIMULUS>
		<AUD_STIMULUS><![CDATA[GL_movement.mp3]]></AUD_STIMULUS>
		<AUD_STIMULUS><![CDATA[GL_ to light.mp3]]></AUD_STIMULUS>
		<AUD_STIMULUS><![CDATA[GL_safety.mp3]]></AUD_STIMULUS>
	</QREC>
	<QREC on="1">
		<A_Type><![CDATA[RP]]></A_Type>
		<UPDATED><![CDATA[Dec 17]]></UPDATED>
		<DEV_COMMENT dir="ltr" esbox="0"><![CDATA[OK]]></DEV_COMMENT>
		<STIMULUS dir="ltr" esbox="0"><![CDATA[“Союз” с тремя космонавтами и олимпийским факелом прибыл на Землю]]></STIMULUS>
		<RESPONSE dir="ltr" esbox="0"><![CDATA[http://rus.ruvr.ru/news/2013_11_11/Sojuz-s-tremja-kosmonavtami-i-Olimpijskim-fakelom-pribil-na-Zemlju-4477/]]></RESPONSE>
		<AID dir="ltr" esbox="0"><![CDATA[The Olympic torch was delivered back to Earth]]></AID>
		<OBJECTIVES><![CDATA[]]>
		</OBJECTIVES>
	</QREC>
	<QREC on="1">
		<A_Type><![CDATA[IP]]></A_Type>
		<UPDATED><![CDATA[Dec 17]]></UPDATED>
		<DEV_COMMENT dir="ltr" esbox="0"><![CDATA[OK]]></DEV_COMMENT>
		<FEATURE dir="ltr" esbox="0"><![CDATA[Vocabulary in context related to topic of space and Winter Olympics]]></FEATURE>
		<OBJECTIVES dir="ltr" esbox="0"><![CDATA[Comprehend a news report while focusing on vocabulary related to space and Winter Olympics.]]></OBJECTIVES>
		<COMPETENCE><![CDATA[Lexical]]></COMPETENCE>
		<PUBLICATION dir="ltr" esbox="0"><![CDATA[Voice of Russia]]></PUBLICATION>
		<YEAR dir="ltr" esbox="0"><![CDATA[2013]]></YEAR>
		<AUTHOR dir="ltr" esbox="0"><![CDATA[]]>
		</AUTHOR>
		<DEVELOPER dir="ltr" esbox="0"><![CDATA[Svetlana Pavlov]]></DEVELOPER>
		<TIME_OF_TASK><![CDATA[08:2 hours]]></TIME_OF_TASK>
	</QREC>
	<QREC on="1">
		<A_Type><![CDATA[CO]]></A_Type>
		<UPDATED><![CDATA[Dec 17]]></UPDATED>
		<DEV_COMMENT dir="ltr" esbox="0"><![CDATA[OK]]></DEV_COMMENT>
		<CO_ParaFL dir="ltr" esbox="0"><![CDATA[1. В студии Григорий Шабанов и сегодня в нашем выпуске: Олимпийский огонь светит из космоса. Ракета-носитель с факелом на борту отправилась на околоземную орбиту. </P>
<P>Впервые за всю историю эстафета олимпийского огня достигла космических масштабов. Несколько часов назад ракета-носитель “Союз” с факелом на борту пристыковалась к международной космической станции. Впереди ещё один важный пункт – вынос факела в безвоздушное пространство. </P>]]></CO_ParaFL>
		<CO_ParaXL dir="ltr" esbox="0"><![CDATA[1. This is Grigoryi Shabanov, and the topic of our broadcast today is: the Olympic flame shines from space. The spacecraft with the torch onboard blasted off into the near-Earth orbit. 
<P></P>
<P>The Olympic torch relay is conducted on a such large scale for the first time in history. The spacecraft Soyuz with the torch onboard docked with the International Space Station several hours ago. There is one more important step ahead — to carry the torch into open space. </P>]]></CO_ParaXL>
		<CO_ParaFL dir="ltr" esbox="0"><![CDATA[<P>2. Мария Болявина следит за необычным путешествием главного символа Олимпийских игр.</P>
<P>Корабль “Союз ТМА-11М” пристыковался к МКС в автоматическом режиме через 6 часов после старта. На околоземную орбиту Олимпийский факел доставил интернациональный экипаж длительной экспедиции: космонавт Роскосмоса Михаил Тюрин, астронавт японского космического агенства Каичи Баката и астронавт НАСА Ричард Мастракио. После стыковки космонавты должны проверить герметичность стыковочного узла. </P>]]></CO_ParaFL>
		<CO_ParaXL dir="ltr" esbox="0"><![CDATA[<P>2. Maria Bolyavina follows the unusual trip of the Olympic Games' symbol.</P>
<P>Spaceship Soyuz TMA-11M docked with the ISS via meachanical docking six hours after the launch. The Olympic torch was delivered to the near-Earth orbit by a multinational crew of the long term space mission: Mikhail Tyurin (Roscosmos), Koici Wakata (Japan's JAXA) and Rick Mastracchio (NASA). Astronauts should check the hermetic sealing of the docking unit after the docking. </P>]]></CO_ParaXL>
		<CO_ParaFL dir="ltr" esbox="0"><![CDATA[3. На МКС вновь прибывший экипаж присоединится к тем космонавтам, которые уже находятся на станции: россиянам Олегу Котову, Сергею Рязанскому, Фёдору Юрчихину, американцам Майклу Хопкинсу и Карен Найберг, а также к итальянцу Луке Пармитано. На орбитальной станции будут находиться сразу 9 космонавтов и 3 пристыкованных корабля.]]></CO_ParaFL>
		<CO_ParaXL dir="ltr" esbox="0"><![CDATA[3. The newly arrived crew will join the ISS crewmembers who have already been stationed there: Russians Oleg Kotov, Sergei Ryazansky, and Fyodor Yurchikhin, Americans Michael Hopkins and Karen Nyberg, as well as Italian Luca Parmitano. Simultaneously there will be nine cosmonauts and three docked spaceships at the orbiting station.]]></CO_ParaXL>
		<CO_ParaFL dir="ltr" esbox="0"><![CDATA[4. Напомним, “Союз” с олимпийским огнем стартовал с первой площадки космодрома Байконур, откуда отправлялся в космос Юрий Гагарин. В 8 часов 23 минуты по московскому времени космический корабль вышел на орбиту дальнего сближения с МКС – доложил Земле капитан/командир корабля Михаил Тюрин.]]></CO_ParaFL>
		<CO_ParaXL dir="ltr" esbox="0"><![CDATA[4. Note that the Soyuz with the Olympic torch on board blasted off from the Boikonur Cosmodrome launch pad number one — the same launch pad from which Yuri Gagarin took off into space. The spaceship Commander Mikhail Tyurin reported back to Earth that the spacecraft had reached the rendezvous orbit with the ISS at 8:23 a.m. Moscow time.]]></CO_ParaXL>
		<CO_ParaFL dir="ltr" esbox="0"><![CDATA[5. Этот полёт – знаменательное событие не только в истории российской космонавтики, но и в истории всего олимпийского движения. На МКС эстафету приняли российские космонавты Олег Котов и Сергей Рязанский, которые 9 ноября выйдут с факелом в открытый космос. Зажигать на станции его не будут из соображений безопасности.]]></CO_ParaFL>
		<CO_ParaXL dir="ltr" esbox="0"><![CDATA[5. This flight is a memorable event not only in the history of the Russian space science, but also in the history of the entire Olympic movement. The torch has been taken up by Russian cosmonauts Oleg Kotov and Sergei Ryazansky who will take it on a space walk on November 9. The torch won't be lit inside the ISS because of safety concerns.]]></CO_ParaXL>
		<CO_ParaFL dir="ltr" esbox="0"><![CDATA[6.  11 ноября экипаж в составе россиянина Фёдора Юрчихина, американки Карен Найберг и итальянца Луки Пармитано доставит олимпийский факел на Землю. Именно от него зажгут Олимпийский огонь на церемонии открытия игр в Сочи.]]></CO_ParaFL>
		<CO_ParaXL dir="ltr" esbox="0"><![CDATA[6. The crew consisting of Russia's Fyodor Yurchikhin, American Karen Nyberg and Italy's Luca Parmitano will deliver the torch to Earth on November 11. This is the torch that will be used to light up the Olympic flame at the Sochi Olympics opening ceremony.]]></CO_ParaXL>
		<AUD_STIMULUS><![CDATA[ru_sci214_Source.mp3]]></AUD_STIMULUS>
		<AUD_STIMULUS><![CDATA[SELECT]]></AUD_STIMULUS>
		<VIDEO_CLIP><![CDATA[No Video File]]></VIDEO_CLIP>
		<MODALITY><![CDATA[Audio]]></MODALITY>
	</QREC>
	<QREC on="1">
		<A_Type><![CDATA[OP]]></A_Type>
		<UPDATED><![CDATA[Dec 17]]></UPDATED>
		<DEV_COMMENT dir="ltr" esbox="0"><![CDATA[OK]]></DEV_COMMENT>
	</QREC>
	<QREC>
		<A_Type><![CDATA[]]>
		</A_Type>
	</QREC>
</DB>
